LICENSE.txt
README.md
pyproject.toml
setup.cfg
setup.py
eve_esi_python/__init__.py
eve_esi_python/api_client.py
eve_esi_python/api_response.py
eve_esi_python/configuration.py
eve_esi_python/exceptions.py
eve_esi_python/py.typed
eve_esi_python/rest.py
eve_esi_python.egg-info/PKG-INFO
eve_esi_python.egg-info/SOURCES.txt
eve_esi_python.egg-info/dependency_links.txt
eve_esi_python.egg-info/requires.txt
eve_esi_python.egg-info/top_level.txt
eve_esi_python/api/__init__.py
eve_esi_python/api/alliance_api.py
eve_esi_python/api/assets_api.py
eve_esi_python/api/calendar_api.py
eve_esi_python/api/character_api.py
eve_esi_python/api/clones_api.py
eve_esi_python/api/contacts_api.py
eve_esi_python/api/contracts_api.py
eve_esi_python/api/corporation_api.py
eve_esi_python/api/dogma_api.py
eve_esi_python/api/faction_warfare_api.py
eve_esi_python/api/fittings_api.py
eve_esi_python/api/fleets_api.py
eve_esi_python/api/incursions_api.py
eve_esi_python/api/industry_api.py
eve_esi_python/api/insurance_api.py
eve_esi_python/api/killmails_api.py
eve_esi_python/api/location_api.py
eve_esi_python/api/loyalty_api.py
eve_esi_python/api/mail_api.py
eve_esi_python/api/market_api.py
eve_esi_python/api/planetary_interaction_api.py
eve_esi_python/api/routes_api.py
eve_esi_python/api/search_api.py
eve_esi_python/api/skills_api.py
eve_esi_python/api/sovereignty_api.py
eve_esi_python/api/status_api.py
eve_esi_python/api/universe_api.py
eve_esi_python/api/user_interface_api.py
eve_esi_python/api/wallet_api.py
eve_esi_python/api/wars_api.py
eve_esi_python/models/__init__.py
eve_esi_python/models/alliances_alliance_id_contacts_get_inner.py
eve_esi_python/models/alliances_alliance_id_contacts_labels_get_inner.py
eve_esi_python/models/alliances_alliance_id_get.py
eve_esi_python/models/alliances_alliance_id_icons_get.py
eve_esi_python/models/characters_affiliation_post_inner.py
eve_esi_python/models/characters_character_id_agents_research_get_inner.py
eve_esi_python/models/characters_character_id_assets_get_inner.py
eve_esi_python/models/characters_character_id_assets_locations_post_inner.py
eve_esi_python/models/characters_character_id_assets_locations_post_inner_position.py
