Metadata-Version: 2.1
Name: eve-esi-python
Version: 0.1.0
Summary: EVE Stellar Information (ESI) - tranquility
Home-page: https://github.com/puffingprie/eve-esi-python
Author: puffingprie
Author-email: puffingprie <morte1916@gmail.com>
License: BSD-3-Clause
Project-URL: Repository, https://github.com/puffingprie/eve-esi-python
Keywords: OpenAPI,OpenAPI-Generator,EVE Stellar Information (ESI) - tranquility
Requires-Python: >=3.9
License-File: LICENSE.txt
